{
  "kind": "singleType",
  "collectionName": "login_pages",
  "info": {
    "singularName": "login-page",
    "pluralName": "login-pages",
    "displayName": "Login page",
    "description": ""
  },
  "options": {
    "draftAndPublish": true
  },
  "pluginOptions": {
    "i18n": {
      "localized": true
    }
  },
  "attributes": {
    "formFields": {
      "type": "component",
      "repeatable": true,
      "pluginOptions": {
        "i18n": {
          "localized": true
        }
      },
      "component": "elements.input"
    },
    "providers": {
      "type": "component",
      "repeatable": true,
      "pluginOptions": {
        "i18n": {
          "localized": true
        }
      },
      "component": "complex.providers"
    },
    "submitBtn": {
      "type": "component",
      "repeatable": false,
      "pluginOptions": {
        "i18n": {
          "localized": true
        }
      },
      "component": "elements.button"
    },
    "additionalLinks": {
      "type": "component",
      "repeatable": true,
      "pluginOptions": {
        "i18n": {
          "localized": true
        }
      },
      "component": "elements.link"
    },
    "seo": {
      "type": "component",
      "repeatable": false,
      "pluginOptions": {
        "i18n": {
          "localized": true
        }
      },
      "component": "shared.seo"
    },
    "cover": {
      "allowedTypes": [
        "images",
        "files",
        "videos",
        "audios"
      ],
      "type": "media",
      "multiple": false,
      "pluginOptions": {
        "i18n": {
          "localized": false
        }
      }
    }
  }
}
